imagereader/__init__.py
imagereader/core.py
imagereader-1.0.1.dist-info/LICENSE
imagereader-1.0.1.dist-info/METADATA
imagereader-1.0.1.dist-info/WHEEL
imagereader-1.0.1.dist-info/top_level.txt
imagereader-1.0.1.dist-info/RECORD
